MANIFEST.in
README.rst
setup.py
keras_biological_gaps_sequence/__init__.py
keras_biological_gaps_sequence/__version__.py
keras_biological_gaps_sequence/biological_gaps_sequence.py
keras_biological_gaps_sequence.egg-info/PKG-INFO
keras_biological_gaps_sequence.egg-info/SOURCES.txt
keras_biological_gaps_sequence.egg-info/dependency_links.txt
keras_biological_gaps_sequence.egg-info/requires.txt
keras_biological_gaps_sequence.egg-info/top_level.txt
keras_biological_gaps_sequence/datasets/hg19_hg38.bed