Metadata-Version: 2.1
Name: keras-biological-gaps-sequence
Version: 1.0.3
Summary: Python package to generate on-hot encoded biological gaps to use for training and prediction.
Home-page: https://github.com/LucaCappelletti94/keras_biological_gaps_sequences
Author: LucaCappelletti94
Author-email: cappelletti.luca94@gmail.com
License: MIT
Platform: UNKNOWN
Classifier: Development Status :: 3 - Alpha
Classifier: License :: OSI Approved :: MIT License
Classifier: Programming Language :: Python :: 3
Provides-Extra: test
